{
	"name": "metadata",
	"properties": {
		"linkedServiceName": {
			"referenceName": "mylakeplace31",
			"type": "LinkedServiceReference"
		},
		"parameters": {
			"year": {
				"type": "string"
			}
		},
		"annotations": [],
		"type": "Binary",
		"typeProperties": {
			"location": {
				"type": "AzureBlobFSLocation",
				"folderPath": {
					"value": "@concat('trip-data/', dataset().year)",
					"type": "Expression"
				},
				"fileSystem": "bronze"
			}
		}
	},
	"type": "Microsoft.DataFactory/factories/datasets"
}